flask_bundler/__init__.py
Flask_Bundler-1.0.2.dist-info/METADATA
Flask_Bundler-1.0.2.dist-info/WHEEL
Flask_Bundler-1.0.2.dist-info/top_level.txt
Flask_Bundler-1.0.2.dist-info/RECORD
