Metadata-Version: 2.1
Name: Flask-Bundler
Version: 1.0.2
Summary: Flask extension to serve Webpack bundles
Home-page: http://github.com/emdemir/Flask-Bundler/
Author: Efe Mert Demir
Author-email: efemertdemir@hotmail.com
License: BSD
Platform: any
Classifier: Environment :: Web Environment
Classifier: Intended Audience :: Developers
Classifier: License :: OSI Approved :: BSD License
Classifier: Operating System :: OS Independent
Classifier: Programming Language :: Python
Classifier: Topic :: Internet :: WWW/HTTP :: Dynamic Content
Classifier: Topic :: Software Development :: Libraries :: Python Modules
Requires-Dist: Flask
